Xiaoimage/__init__.py
Xiaoimage/bs.py
Xiaoimage/music.py
Xiaoimage-2.1.9.data/scripts/baidu-image.py
Xiaoimage-2.1.9.data/scripts/load-image.py
Ximg/__init__.py
Ximg/bs.py
Ximg/music.py
Xiaoimage-2.1.9.dist-info/METADATA
Xiaoimage-2.1.9.dist-info/WHEEL
Xiaoimage-2.1.9.dist-info/entry_points.txt
Xiaoimage-2.1.9.dist-info/top_level.txt
Xiaoimage-2.1.9.dist-info/RECORD
