Metadata-Version: 2.1
Name: Xiaoimage
Version: 2.1.9
Author: Wells Xiao
Requires-Dist: Flask
Requires-Dist: requests
Requires-Dist: BeautifulSoup4
